p3k_app-3.12.0b0.dist-info/METADATA
p3k_app-3.12.0b0.dist-info/WHEEL
p3k_app-3.12.0b0.dist-info/entry_points.txt
p3k_app/__init__.py
p3k_app/p09.py
p3k_app-3.12.0b0.dist-info/RECORD
