Metadata-Version: 2.1
Name: p3k_app
Version: 3.12.0b0
Summary: Python 3000 CLI
Author-Email: "D. Alex Graham" <alex@aode.space>
License: MIT
Requires-Python: >=3.12
Requires-Dist: rich>=13.9.2
Requires-Dist: version3900>=3.9.0
Requires-Dist: typer>=0.12.5
Requires-Dist: p12>=3.12.0.dev0
